word_text_counter/__init__.py
word_text_counter/data/__init__.py
word_text_counter/data/flatland.txt
word_text_counter/data/lostworld.txt
word_text_counter/data/time_machine.txt
word_text_counter/datasets.py
word_text_counter/word_text_counter.py
word_text_counter-0.3.0.dist-info/LICENSE
word_text_counter-0.3.0.dist-info/WHEEL
word_text_counter-0.3.0.dist-info/METADATA
word_text_counter-0.3.0.dist-info/RECORD
