Metadata-Version: 2.1
Name: word-text-counter
Version: 0.3.0
Summary: Calculate word counts in a text file!
License: MIT
Author: Sumbono
Requires-Python: >=3.9,<4.0
Classifier: License :: OSI Approved :: MIT License
Classifier: Programming Language :: Python :: 3
Classifier: Programming Language :: Python :: 3.10
Classifier: Programming Language :: Python :: 3.9
